[
  {
    "id": "1",
    "title": "Addis Jazz Festival 2024",
    "date": "2025-10-21T19:00:00Z",
    "location": {
      "name": "Addis Ababa Stadium",
      "coordinates": ["9.0192", "38.7525"]
    },
    "category": "music",
    "price": "500",
    "currency": "ETB",
    "description": "Join us for an unforgettable evening of smooth jazz featuring local and international artists.",
    "organizer": "Addis Jazz Society",
    "featured": "true",
    "isOnline": "false",
    "requiresRegistration": "true",
    "showOnMap": "true",
    "allowZoom": "true",
    "showMarker": "true"
  },
  {
    "id": "2",
    "title": "Tech Startup Meetup",
    "date": "2025-10-22T14:00:00Z",
    "location": {
      "name": "Sheraton Addis Hotel",
      "coordinates": ["9.0348", "38.7616"]
    },
    "category": "technology",
    "price": "0",
    "currency": "ETB",
    "description": "Connect with fellow entrepreneurs and tech enthusiasts.",
    "organizer": "Ethiopian Tech Community",
    "featured": "false",
    "isOnline": "true",
    "requiresRegistration": "false",
    "showOnMap": "true",
    "allowZoom": "false",
    "showMarker": "true"
  },
  {
    "id": "3",
    "title": "Ethiopian Coffee Ceremony",
    "date": "2025-10-23T10:00:00Z",
    "location": {
      "name": "Tomoca Coffee Shop",
      "coordinates": ["9.0307", "38.7578"]
    },
    "category": "food",
    "price": "200",
    "currency": "ETB",
    "description": "Learn the traditional Ethiopian coffee ceremony.",
    "organizer": "Tomoca Coffee",
    "featured": "true",
    "isOnline": "false",
    "requiresRegistration": "true",
    "showOnMap": "true",
    "allowZoom": "true",
    "showMarker": "false"
  },
  {
    "id": "4",
    "title": "Addis Art Gallery Exhibition",
    "date": "2025-10-24T16:00:00Z",
    "location": {
      "name": "National Museum of Ethiopia",
      "coordinates": ["9.0348", "38.7525"]
    },
    "category": "art",
    "price": "150",
    "currency": "ETB",
    "description": "Contemporary Ethiopian art exhibition featuring local artists.",
    "organizer": "Addis Art Collective",
    "featured": "false",
    "isOnline": "false",
    "requiresRegistration": "false",
    "showOnMap": "true",
    "allowZoom": "true",
    "showMarker": "true"
  },
  {
    "id": "5",
    "title": "Ethiopian Cultural Dance Workshop",
    "date": "2025-10-25T18:30:00Z",
    "location": {
      "name": "Hager Fikir Theatre",
      "coordinates": ["9.0192", "38.7616"]
    },
    "category": "culture",
    "price": "300",
    "currency": "ETB",
    "description": "Learn traditional Ethiopian dances from professional instructors.",
    "organizer": "Ethiopian Cultural Center",
    "featured": "true",
    "isOnline": "false",
    "requiresRegistration": "true",
    "showOnMap": "true",
    "allowZoom": "false",
    "showMarker": "true"
  },
  {
    "id": "6",
    "title": "Business Networking Summit",
    "date": "2025-10-26T09:00:00Z",
    "location": {
      "name": "Hilton Addis Ababa",
      "coordinates": ["9.0307", "38.7578"]
    },
    "category": "business",
    "price": "800",
    "currency": "ETB",
    "description": "Connect with business leaders and entrepreneurs across Ethiopia.",
    "organizer": "Ethiopian Business Association",
    "featured": "false",
    "isOnline": "true",
    "requiresRegistration": "true",
    "showOnMap": "true",
    "allowZoom": "true",
    "showMarker": "true"
  }
]
